devops_utils/__init__.py
devops_utils/sanitizer.py
devops_utils/utils.py
devops_utils-0.0.6.dist-info/LICENSE
devops_utils-0.0.6.dist-info/METADATA
devops_utils-0.0.6.dist-info/WHEEL
devops_utils-0.0.6.dist-info/top_level.txt
devops_utils-0.0.6.dist-info/RECORD
