Metadata-Version: 2.1
Name: devops-utils
Version: 0.0.6
Summary: A set of utility scripts for DevOps
Home-page: https://github.com/carneirofc/devops-utils
Download-URL: https://github.com/carneirofc/devops-utils
Author: Cláudio Ferreira Carneiro
Author-email: claudiofcarneiro@hotmail.com
License: MIT
Classifier: Programming Language :: Python :: 3
Requires-Python: >=3.6
License-File: LICENSE
Requires-Dist: PyYAML
